dslab/__init__.py
dslab/dbpath.py
datasentics_lab-0.1.3.dist-info/LICENSE.md
datasentics_lab-0.1.3.dist-info/WHEEL
datasentics_lab-0.1.3.dist-info/METADATA
datasentics_lab-0.1.3.dist-info/RECORD
