Metadata-Version: 2.1
Name: datasentics-lab
Version: 0.1.3
Summary: DataSentics Lab - experimental open-source repo
Home-page: https://github.com/DataSentics/datasentics-lab
License: MIT
Author: Adam Volny
Author-email: adam.volny@datasentics.com
Requires-Python: >=3.7.1,<4.0.0
Classifier: License :: OSI Approved :: MIT License
Classifier: Operating System :: OS Independent
Classifier: Programming Language :: Python :: 3
Classifier: Programming Language :: Python :: 3.8
Classifier: Programming Language :: Python :: 3.9
Requires-Dist: azure-storage-blob (>=12.8.0,<13.0.0)
Requires-Dist: requests (>=2.25.1,<3.0.0)
Project-URL: Repository, https://github.com/DataSentics/datasentics-lab
